{
  "project_info": {
    "project_number": "782549800264",
    "project_id": "vaimovie",
    "storage_bucket": "vaimovie.appspot.com"
  },
  "client": [
    {
      "client_info": {
        "mobilesdk_app_id": "1:782549800264:android:c625a9a95be21e46ec4f7d",
        "android_client_info": {
          "package_name": "com.vaimovie"
        }
      },
      "oauth_client": [
        {
          "client_id": "782549800264-u7s48k45c9b3mg6qhfrrfuhsntnrl5fb.apps.googleusercontent.com",
          "client_type": 1,
          "android_info": {
            "package_name": "com.vaimovie",
            "certificate_hash": "5e8f16062ea3cd2c4a0d547876baa6f38cabf625"
          }
        },
        {
          "client_id": "782549800264-rg542b54onshq736kio1pg9m8klvln4s.apps.googleusercontent.com",
          "client_type": 3
        }
      ],
      "api_key": [
        {
          "current_key": "AIzaSyDqwUHy8HgWQF9m1pbHKitJWyJEBSkKsZA"
        }
      ],
      "services": {
        "appinvite_service": {
          "other_platform_oauth_client": [
            {
              "client_id": "782549800264-rg542b54onshq736kio1pg9m8klvln4s.apps.googleusercontent.com",
              "client_type": 3
            }
          ]
        }
      }
    }
  ],
  "configuration_version": "1"
}